[{"anno": "2024", "categoria": "ACI", "fascia_importo": "(0-25]", "numero_transazioni": 13768408}, {"anno": "2024", "categoria": "ACI", "fascia_importo": "(100-200]", "numero_transazioni": 13056022}, {"anno": "2024", "categoria": "ACI", "fascia_importo": "(200-500]", "numero_transazioni": 12146031}, {"anno": "2024", "categoria": "ACI", "fascia_importo": "(25-50]", "numero_transazioni": 4751414}, {"anno": "2024", "categoria": "ACI", "fascia_importo": "(50-100]", "numero_transazioni": 3976638}, {"anno": "2024", "categoria": "ACI", "fascia_importo": "(500-1000]", "numero_transazioni": 1233382}, {"anno": "2024", "categoria": "ACI", "fascia_importo": ">1000", "numero_transazioni": 110457}, {"anno": "2024", "categoria": "Altri enti territoriali", "fascia_importo": "(0-25]", "numero_transazioni": 1224551}, {"anno": "2024", "categoria": "Altri enti territoriali", "fascia_importo": "(100-200]", "numero_transazioni": 1025804}, {"anno": "2024", "categoria": "Altri enti territoriali", "fascia_importo": "(200-500]", "numero_transazioni": 647717}, {"anno": "2024", "categoria": "Altri enti territoriali", "fascia_importo": "(25-50]", "numero_transazioni": 1295908}, {"anno": "2024", "categoria": "Altri enti territoriali", "fascia_importo": "(50-100]", "numero_transazioni": 1248543}, {"anno": "2024", "categoria": "Altri enti territoriali", "fascia_importo": "(500-1000]", "numero_transazioni": 109383}, {"anno": "2024", "categoria": "Altri enti territoriali", "fascia_importo": ">1000", "numero_transazioni": 117537}, {"anno": "2024", "categoria": "Comuni", "fascia_importo": "(0-25]", "numero_transazioni": 7942608}, {"anno": "2024", "categoria": "Comuni", "fascia_importo": "(100-200]", "numero_transazioni": 11530739}, {"anno": "2024", "categoria": "Comuni", "fascia_importo": "(200-500]", "numero_transazioni": 6074490}, {"anno": "2024", "categoria": "Comuni", "fascia_importo": "(25-50]", "numero_transazioni": 13201211}, {"anno": "2024", "categoria": "Comuni", "fascia_importo": "(50-100]", "numero_transazioni": 16237496}, {"anno": "2024", "categoria": "Comuni", "fascia_importo": "(500-1000]", "numero_transazioni": 1278419}, {"anno": "2024", "categoria": "Comuni", "fascia_importo": ">1000", "numero_transazioni": 818428}, {"anno": "2024", "categoria": "Consorzi universitari", "fascia_importo": "(0-25]", "numero_transazioni": 74834}, {"anno": "2024", "categoria": "Consorzi universitari", "fascia_importo": "(100-200]", "numero_transazioni": 200960}, {"anno": "2024", "categoria": "Consorzi universitari", "fascia_importo": "(200-500]", "numero_transazioni": 28749}, {"anno": "2024", "categoria": "Consorzi universitari", "fascia_importo": "(25-50]", "numero_transazioni": 21657}, {"anno": "2024", "categoria": "Consorzi universitari", "fascia_importo": "(50-100]", "numero_transazioni": 15530}, {"anno": "2024", "categoria": "Consorzi universitari", "fascia_importo": "(500-1000]", "numero_transazioni": 4130}, {"anno": "2024", "categoria": "Consorzi universitari", "fascia_importo": ">1000", "numero_transazioni": 3842}, {"anno": "2024", "categoria": "Enti comunali", "fascia_importo": "(0-25]", "numero_transazioni": 45834}, {"anno": "2024", "categoria": "Enti comunali", "fascia_importo": "(100-200]", "numero_transazioni": 45948}, {"anno": "2024", "categoria": "Enti comunali", "fascia_importo": "(200-500]", "numero_transazioni": 17234}, {"anno": "2024", "categoria": "Enti comunali", "fascia_importo": "(25-50]", "numero_transazioni": 54345}, {"anno": "2024", "categoria": "Enti comunali", "fascia_importo": "(50-100]", "numero_transazioni": 62459}, {"anno": "2024", "categoria": "Enti comunali", "fascia_importo": "(500-1000]", "numero_transazioni": 2683}, {"anno": "2024", "categoria": "Enti comunali", "fascia_importo": ">1000", "numero_transazioni": 2270}, {"anno": "2024", "categoria": "Enti provinciali", "fascia_importo": "(0-25]", "numero_transazioni": 774}, {"anno": "2024", "categoria": "Enti provinciali", "fascia_importo": "(100-200]", "numero_transazioni": 754}, {"anno": "2024", "categoria": "Enti provinciali", "fascia_importo": "(200-500]", "numero_transazioni": 623}, {"anno": "2024", "categoria": "Enti provinciali", "fascia_importo": "(25-50]", "numero_transazioni": 3214}, {"anno": "2024", "categoria": "Enti provinciali", "fascia_importo": "(50-100]", "numero_transazioni": 2641}, {"anno": "2024", "categoria": "Enti provinciali", "fascia_importo": "(500-1000]", "numero_transazioni": 541}, {"anno": "2024", "categoria": "Enti provinciali", "fascia_importo": ">1000", "numero_transazioni": 297}, {"anno": "2024", "categoria": "Enti regionali", "fascia_importo": "(0-25]", "numero_transazioni": 164}, {"anno": "2024", "categoria": "Enti regionali", "fascia_importo": "(100-200]", "numero_transazioni": 63}, {"anno": "2024", "categoria": "Enti regionali", "fascia_importo": "(200-500]", "numero_transazioni": 69}, {"anno": "2024", "categoria": "Enti regionali", "fascia_importo": "(25-50]", "numero_transazioni": 25}, {"anno": "2024", "categoria": "Enti regionali", "fascia_importo": "(50-100]", "numero_transazioni": 50}, {"anno": "2024", "categoria": "Enti regionali", "fascia_importo": "(500-1000]", "numero_transazioni": 34}, {"anno": "2024", "categoria": "Enti regionali", "fascia_importo": ">1000", "numero_transazioni": 167}, {"anno": "2024", "categoria": "Ordini, collegi e consigli professionali", "fascia_importo": "(0-25]", "numero_transazioni": 452359}, {"anno": "2024", "categoria": "Ordini, collegi e consigli professionali", "fascia_importo": "(100-200]", "numero_transazioni": 1155562}, {"anno": "2024", "categoria": "Ordini, collegi e consigli professionali", "fascia_importo": "(200-500]", "numero_transazioni": 458358}, {"anno": "2024", "categoria": "Ordini, collegi e consigli professionali", "fascia_importo": "(25-50]", "numero_transazioni": 292043}, {"anno": "2024", "categoria": "Ordini, collegi e consigli professionali", "fascia_importo": "(50-100]", "numero_transazioni": 776005}, {"anno": "2024", "categoria": "Ordini, collegi e consigli professionali", "fascia_importo": "(500-1000]", "numero_transazioni": 12722}, {"anno": "2024", "categoria": "Ordini, collegi e consigli professionali", "fascia_importo": ">1000", "numero_transazioni": 13418}, {"anno": "2024", "categoria": "Province", "fascia_importo": "(0-25]", "numero_transazioni": 152370}, {"anno": "2024", "categoria": "Province", "fascia_importo": "(100-200]", "numero_transazioni": 407107}, {"anno": "2024", "categoria": "Province", "fascia_importo": "(200-500]", "numero_transazioni": 193668}, {"anno": "2024", "categoria": "Province", "fascia_importo": "(25-50]", "numero_transazioni": 733750}, {"anno": "2024", "categoria": "Province", "fascia_importo": "(50-100]", "numero_transazioni": 474040}, {"anno": "2024", "categoria": "Province", "fascia_importo": "(500-1000]", "numero_transazioni": 34475}, {"anno": "2024", "categoria": "Province", "fascia_importo": ">1000", "numero_transazioni": 24956}, {"anno": "2024", "categoria": "Pubbliche amministrazioni centrali", "fascia_importo": "(0-25]", "numero_transazioni": 50591373}, {"anno": "2024", "categoria": "Pubbliche amministrazioni centrali", "fascia_importo": "(100-200]", "numero_transazioni": 10001970}, {"anno": "2024", "categoria": "Pubbliche amministrazioni centrali", "fascia_importo": "(200-500]", "numero_transazioni": 9286648}, {"anno": "2024", "categoria": "Pubbliche amministrazioni centrali", "fascia_importo": "(25-50]", "numero_transazioni": 14200958}, {"anno": "2024", "categoria": "Pubbliche amministrazioni centrali", "fascia_importo": "(50-100]", "numero_transazioni": 16101416}, {"anno": "2024", "categoria": "Pubbliche amministrazioni centrali", "fascia_importo": "(500-1000]", "numero_transazioni": 3679238}, {"anno": "2024", "categoria": "Pubbliche amministrazioni centrali", "fascia_importo": ">1000", "numero_transazioni": 2525670}, {"anno": "2024", "categoria": "Regioni", "fascia_importo": "(0-25]", "numero_transazioni": 1293492}, {"anno": "2024", "categoria": "Regioni", "fascia_importo": "(100-200]", "numero_transazioni": 2820561}, {"anno": "2024", "categoria": "Regioni", "fascia_importo": "(200-500]", "numero_transazioni": 2427943}, {"anno": "2024", "categoria": "Regioni", "fascia_importo": "(25-50]", "numero_transazioni": 917096}, {"anno": "2024", "categoria": "Regioni", "fascia_importo": "(50-100]", "numero_transazioni": 1184787}, {"anno": "2024", "categoria": "Regioni", "fascia_importo": "(500-1000]", "numero_transazioni": 195612}, {"anno": "2024", "categoria": "Regioni", "fascia_importo": ">1000", "numero_transazioni": 95708}, {"anno": "2024", "categoria": "Ricerca", "fascia_importo": "(0-25]", "numero_transazioni": 4277}, {"anno": "2024", "categoria": "Ricerca", "fascia_importo": "(100-200]", "numero_transazioni": 344}, {"anno": "2024", "categoria": "Ricerca", "fascia_importo": "(200-500]", "numero_transazioni": 1992}, {"anno": "2024", "categoria": "Ricerca", "fascia_importo": "(25-50]", "numero_transazioni": 460}, {"anno": "2024", "categoria": "Ricerca", "fascia_importo": "(50-100]", "numero_transazioni": 588}, {"anno": "2024", "categoria": "Ricerca", "fascia_importo": "(500-1000]", "numero_transazioni": 676}, {"anno": "2024", "categoria": "Ricerca", "fascia_importo": ">1000", "numero_transazioni": 1198}, {"anno": "2024", "categoria": "Salute centrale", "fascia_importo": "(0-25]", "numero_transazioni": 2498230}, {"anno": "2024", "categoria": "Salute centrale", "fascia_importo": "(100-200]", "numero_transazioni": 670997}, {"anno": "2024", "categoria": "Salute centrale", "fascia_importo": "(200-500]", "numero_transazioni": 121778}, {"anno": "2024", "categoria": "Salute centrale", "fascia_importo": "(25-50]", "numero_transazioni": 1648413}, {"anno": "2024", "categoria": "Salute centrale", "fascia_importo": "(50-100]", "numero_transazioni": 367899}, {"anno": "2024", "categoria": "Salute centrale", "fascia_importo": "(500-1000]", "numero_transazioni": 15282}, {"anno": "2024", "categoria": "Salute centrale", "fascia_importo": ">1000", "numero_transazioni": 29452}, {"anno": "2024", "categoria": "Salute locale", "fascia_importo": "(0-25]", "numero_transazioni": 5263418}, {"anno": "2024", "categoria": "Salute locale", "fascia_importo": "(100-200]", "numero_transazioni": 848415}, {"anno": "2024", "categoria": "Salute locale", "fascia_importo": "(200-500]", "numero_transazioni": 139788}, {"anno": "2024", "categoria": "Salute locale", "fascia_importo": "(25-50]", "numero_transazioni": 3984700}, {"anno": "2024", "categoria": "Salute locale", "fascia_importo": "(50-100]", "numero_transazioni": 1348208}, {"anno": "2024", "categoria": "Salute locale", "fascia_importo": "(500-1000]", "numero_transazioni": 26078}, {"anno": "2024", "categoria": "Salute locale", "fascia_importo": ">1000", "numero_transazioni": 36779}, {"anno": "2024", "categoria": "Salute regionale", "fascia_importo": "(0-25]", "numero_transazioni": 33505}, {"anno": "2024", "categoria": "Salute regionale", "fascia_importo": "(100-200]", "numero_transazioni": 12}, {"anno": "2024", "categoria": "Salute regionale", "fascia_importo": "(200-500]", "numero_transazioni": 36}, {"anno": "2024", "categoria": "Salute regionale", "fascia_importo": "(25-50]", "numero_transazioni": 11}, {"anno": "2024", "categoria": "Salute regionale", "fascia_importo": "(50-100]", "numero_transazioni": 11}, {"anno": "2024", "categoria": "Salute regionale", "fascia_importo": "(500-1000]", "numero_transazioni": 183}, {"anno": "2024", "categoria": "Salute regionale", "fascia_importo": ">1000", "numero_transazioni": 530}, {"anno": "2024", "categoria": "Salute servizi", "fascia_importo": "(0-25]", "numero_transazioni": 80303}, {"anno": "2024", "categoria": "Salute servizi", "fascia_importo": "(100-200]", "numero_transazioni": 39318}, {"anno": "2024", "categoria": "Salute servizi", "fascia_importo": "(200-500]", "numero_transazioni": 45576}, {"anno": "2024", "categoria": "Salute servizi", "fascia_importo": "(25-50]", "numero_transazioni": 62255}, {"anno": "2024", "categoria": "Salute servizi", "fascia_importo": "(50-100]", "numero_transazioni": 46958}, {"anno": "2024", "categoria": "Salute servizi", "fascia_importo": "(500-1000]", "numero_transazioni": 20113}, {"anno": "2024", "categoria": "Salute servizi", "fascia_importo": ">1000", "numero_transazioni": 70025}, {"anno": "2024", "categoria": "Scuola", "fascia_importo": "(0-25]", "numero_transazioni": 9785874}, {"anno": "2024", "categoria": "Scuola", "fascia_importo": "(100-200]", "numero_transazioni": 1716877}, {"anno": "2024", "categoria": "Scuola", "fascia_importo": "(200-500]", "numero_transazioni": 1247597}, {"anno": "2024", "categoria": "Scuola", "fascia_importo": "(25-50]", "numero_transazioni": 3105164}, {"anno": "2024", "categoria": "Scuola", "fascia_importo": "(50-100]", "numero_transazioni": 1605260}, {"anno": "2024", "categoria": "Scuola", "fascia_importo": "(500-1000]", "numero_transazioni": 155503}, {"anno": "2024", "categoria": "Scuola", "fascia_importo": ">1000", "numero_transazioni": 26467}, {"anno": "2024", "categoria": "Tutte", "fascia_importo": "(0-25]", "numero_transazioni": 108897222}, {"anno": "2024", "categoria": "Tutte", "fascia_importo": "(100-200]", "numero_transazioni": 81532412}, {"anno": "2024", "categoria": "Tutte", "fascia_importo": "(200-500]", "numero_transazioni": 50373577}, {"anno": "2024", "categoria": "Tutte", "fascia_importo": "(25-50]", "numero_transazioni": 75370965}, {"anno": "2024", "categoria": "Tutte", "fascia_importo": "(50-100]", "numero_transazioni": 87760797}, {"anno": "2024", "categoria": "Tutte", "fascia_importo": "(500-1000]", "numero_transazioni": 11089478}, {"anno": "2024", "categoria": "Tutte", "fascia_importo": ">1000", "numero_transazioni": 7096029}, {"anno": "2024", "categoria": "Università", "fascia_importo": "(0-25]", "numero_transazioni": 1034430}, {"anno": "2024", "categoria": "Università", "fascia_importo": "(100-200]", "numero_transazioni": 1591810}, {"anno": "2024", "categoria": "Università", "fascia_importo": "(200-500]", "numero_transazioni": 1217782}, {"anno": "2024", "categoria": "Università", "fascia_importo": "(25-50]", "numero_transazioni": 774803}, {"anno": "2024", "categoria": "Università", "fascia_importo": "(50-100]", "numero_transazioni": 562440}, {"anno": "2024", "categoria": "Università", "fascia_importo": "(500-1000]", "numero_transazioni": 1050400}, {"anno": "2024", "categoria": "Università", "fascia_importo": ">1000", "numero_transazioni": 650006}, {"anno": "2024", "categoria": "Utility", "fascia_importo": "(0-25]", "numero_transazioni": 14650414}, {"anno": "2024", "categoria": "Utility", "fascia_importo": "(100-200]", "numero_transazioni": 36419149}, {"anno": "2024", "categoria": "Utility", "fascia_importo": "(200-500]", "numero_transazioni": 16317498}, {"anno": "2024", "categoria": "Utility", "fascia_importo": "(25-50]", "numero_transazioni": 30323538}, {"anno": "2024", "categoria": "Utility", "fascia_importo": "(50-100]", "numero_transazioni": 43749828}, {"anno": "2024", "categoria": "Utility", "fascia_importo": "(500-1000]", "numero_transazioni": 3270624}, {"anno": "2024", "categoria": "Utility", "fascia_importo": ">1000", "numero_transazioni": 2568822}, {"anno": "2025", "categoria": "ACI", "fascia_importo": "(0-25]", "numero_transazioni": 14257710}, {"anno": "2025", "categoria": "ACI", "fascia_importo": "(100-200]", "numero_transazioni": 13244239}, {"anno": "2025", "categoria": "ACI", "fascia_importo": "(200-500]", "numero_transazioni": 12175130}, {"anno": "2025", "categoria": "ACI", "fascia_importo": "(25-50]", "numero_transazioni": 4937207}, {"anno": "2025", "categoria": "ACI", "fascia_importo": "(50-100]", "numero_transazioni": 4165250}, {"anno": "2025", "categoria": "ACI", "fascia_importo": "(500-1000]", "numero_transazioni": 1246793}, {"anno": "2025", "categoria": "ACI", "fascia_importo": ">1000", "numero_transazioni": 115177}, {"anno": "2025", "categoria": "Altri enti territoriali", "fascia_importo": "(0-25]", "numero_transazioni": 1859708}, {"anno": "2025", "categoria": "Altri enti territoriali", "fascia_importo": "(100-200]", "numero_transazioni": 1094629}, {"anno": "2025", "categoria": "Altri enti territoriali", "fascia_importo": "(200-500]", "numero_transazioni": 728695}, {"anno": "2025", "categoria": "Altri enti territoriali", "fascia_importo": "(25-50]", "numero_transazioni": 1392464}, {"anno": "2025", "categoria": "Altri enti territoriali", "fascia_importo": "(50-100]", "numero_transazioni": 1341226}, {"anno": "2025", "categoria": "Altri enti territoriali", "fascia_importo": "(500-1000]", "numero_transazioni": 129710}, {"anno": "2025", "categoria": "Altri enti territoriali", "fascia_importo": ">1000", "numero_transazioni": 150815}, {"anno": "2025", "categoria": "Comuni", "fascia_importo": "(0-25]", "numero_transazioni": 8811939}, {"anno": "2025", "categoria": "Comuni", "fascia_importo": "(100-200]", "numero_transazioni": 13663778}, {"anno": "2025", "categoria": "Comuni", "fascia_importo": "(200-500]", "numero_transazioni": 7235288}, {"anno": "2025", "categoria": "Comuni", "fascia_importo": "(25-50]", "numero_transazioni": 14266394}, {"anno": "2025", "categoria": "Comuni", "fascia_importo": "(50-100]", "numero_transazioni": 17659843}, {"anno": "2025", "categoria": "Comuni", "fascia_importo": "(500-1000]", "numero_transazioni": 1525503}, {"anno": "2025", "categoria": "Comuni", "fascia_importo": ">1000", "numero_transazioni": 973368}, {"anno": "2025", "categoria": "Consorzi universitari", "fascia_importo": "(0-25]", "numero_transazioni": 68342}, {"anno": "2025", "categoria": "Consorzi universitari", "fascia_importo": "(100-200]", "numero_transazioni": 225039}, {"anno": "2025", "categoria": "Consorzi universitari", "fascia_importo": "(200-500]", "numero_transazioni": 31030}, {"anno": "2025", "categoria": "Consorzi universitari", "fascia_importo": "(25-50]", "numero_transazioni": 21116}, {"anno": "2025", "categoria": "Consorzi universitari", "fascia_importo": "(50-100]", "numero_transazioni": 15836}, {"anno": "2025", "categoria": "Consorzi universitari", "fascia_importo": "(500-1000]", "numero_transazioni": 4512}, {"anno": "2025", "categoria": "Consorzi universitari", "fascia_importo": ">1000", "numero_transazioni": 4889}, {"anno": "2025", "categoria": "Enti comunali", "fascia_importo": "(0-25]", "numero_transazioni": 18401}, {"anno": "2025", "categoria": "Enti comunali", "fascia_importo": "(100-200]", "numero_transazioni": 32940}, {"anno": "2025", "categoria": "Enti comunali", "fascia_importo": "(200-500]", "numero_transazioni": 18162}, {"anno": "2025", "categoria": "Enti comunali", "fascia_importo": "(25-50]", "numero_transazioni": 35277}, {"anno": "2025", "categoria": "Enti comunali", "fascia_importo": "(50-100]", "numero_transazioni": 39534}, {"anno": "2025", "categoria": "Enti comunali", "fascia_importo": "(500-1000]", "numero_transazioni": 2562}, {"anno": "2025", "categoria": "Enti comunali", "fascia_importo": ">1000", "numero_transazioni": 2061}, {"anno": "2025", "categoria": "Enti provinciali", "fascia_importo": "(0-25]", "numero_transazioni": 682}, {"anno": "2025", "categoria": "Enti provinciali", "fascia_importo": "(100-200]", "numero_transazioni": 745}, {"anno": "2025", "categoria": "Enti provinciali", "fascia_importo": "(200-500]", "numero_transazioni": 398}, {"anno": "2025", "categoria": "Enti provinciali", "fascia_importo": "(25-50]", "numero_transazioni": 1610}, {"anno": "2025", "categoria": "Enti provinciali", "fascia_importo": "(50-100]", "numero_transazioni": 1223}, {"anno": "2025", "categoria": "Enti provinciali", "fascia_importo": "(500-1000]", "numero_transazioni": 432}, {"anno": "2025", "categoria": "Enti provinciali", "fascia_importo": ">1000", "numero_transazioni": 272}, {"anno": "2025", "categoria": "Enti regionali", "fascia_importo": "(0-25]", "numero_transazioni": 148}, {"anno": "2025", "categoria": "Enti regionali", "fascia_importo": "(100-200]", "numero_transazioni": 52}, {"anno": "2025", "categoria": "Enti regionali", "fascia_importo": "(200-500]", "numero_transazioni": 51}, {"anno": "2025", "categoria": "Enti regionali", "fascia_importo": "(25-50]", "numero_transazioni": 10}, {"anno": "2025", "categoria": "Enti regionali", "fascia_importo": "(50-100]", "numero_transazioni": 38}, {"anno": "2025", "categoria": "Enti regionali", "fascia_importo": "(500-1000]", "numero_transazioni": 33}, {"anno": "2025", "categoria": "Enti regionali", "fascia_importo": ">1000", "numero_transazioni": 160}, {"anno": "2025", "categoria": "Ordini, collegi e consigli professionali", "fascia_importo": "(0-25]", "numero_transazioni": 521582}, {"anno": "2025", "categoria": "Ordini, collegi e consigli professionali", "fascia_importo": "(100-200]", "numero_transazioni": 1192845}, {"anno": "2025", "categoria": "Ordini, collegi e consigli professionali", "fascia_importo": "(200-500]", "numero_transazioni": 474797}, {"anno": "2025", "categoria": "Ordini, collegi e consigli professionali", "fascia_importo": "(25-50]", "numero_transazioni": 291051}, {"anno": "2025", "categoria": "Ordini, collegi e consigli professionali", "fascia_importo": "(50-100]", "numero_transazioni": 944240}, {"anno": "2025", "categoria": "Ordini, collegi e consigli professionali", "fascia_importo": "(500-1000]", "numero_transazioni": 14268}, {"anno": "2025", "categoria": "Ordini, collegi e consigli professionali", "fascia_importo": ">1000", "numero_transazioni": 14180}, {"anno": "2025", "categoria": "Province", "fascia_importo": "(0-25]", "numero_transazioni": 166867}, {"anno": "2025", "categoria": "Province", "fascia_importo": "(100-200]", "numero_transazioni": 411053}, {"anno": "2025", "categoria": "Province", "fascia_importo": "(200-500]", "numero_transazioni": 191867}, {"anno": "2025", "categoria": "Province", "fascia_importo": "(25-50]", "numero_transazioni": 713121}, {"anno": "2025", "categoria": "Province", "fascia_importo": "(50-100]", "numero_transazioni": 467581}, {"anno": "2025", "categoria": "Province", "fascia_importo": "(500-1000]", "numero_transazioni": 39475}, {"anno": "2025", "categoria": "Province", "fascia_importo": ">1000", "numero_transazioni": 27654}, {"anno": "2025", "categoria": "Pubbliche amministrazioni centrali", "fascia_importo": "(0-25]", "numero_transazioni": 52510277}, {"anno": "2025", "categoria": "Pubbliche amministrazioni centrali", "fascia_importo": "(100-200]", "numero_transazioni": 11188789}, {"anno": "2025", "categoria": "Pubbliche amministrazioni centrali", "fascia_importo": "(200-500]", "numero_transazioni": 10219573}, {"anno": "2025", "categoria": "Pubbliche amministrazioni centrali", "fascia_importo": "(25-50]", "numero_transazioni": 14646268}, {"anno": "2025", "categoria": "Pubbliche amministrazioni centrali", "fascia_importo": "(50-100]", "numero_transazioni": 18781458}, {"anno": "2025", "categoria": "Pubbliche amministrazioni centrali", "fascia_importo": "(500-1000]", "numero_transazioni": 3938357}, {"anno": "2025", "categoria": "Pubbliche amministrazioni centrali", "fascia_importo": ">1000", "numero_transazioni": 2643780}, {"anno": "2025", "categoria": "Regioni", "fascia_importo": "(0-25]", "numero_transazioni": 1508606}, {"anno": "2025", "categoria": "Regioni", "fascia_importo": "(100-200]", "numero_transazioni": 2781039}, {"anno": "2025", "categoria": "Regioni", "fascia_importo": "(200-500]", "numero_transazioni": 2478187}, {"anno": "2025", "categoria": "Regioni", "fascia_importo": "(25-50]", "numero_transazioni": 1058332}, {"anno": "2025", "categoria": "Regioni", "fascia_importo": "(50-100]", "numero_transazioni": 1256224}, {"anno": "2025", "categoria": "Regioni", "fascia_importo": "(500-1000]", "numero_transazioni": 205781}, {"anno": "2025", "categoria": "Regioni", "fascia_importo": ">1000", "numero_transazioni": 107077}, {"anno": "2025", "categoria": "Ricerca", "fascia_importo": "(0-25]", "numero_transazioni": 11786}, {"anno": "2025", "categoria": "Ricerca", "fascia_importo": "(100-200]", "numero_transazioni": 11656}, {"anno": "2025", "categoria": "Ricerca", "fascia_importo": "(200-500]", "numero_transazioni": 5697}, {"anno": "2025", "categoria": "Ricerca", "fascia_importo": "(25-50]", "numero_transazioni": 462}, {"anno": "2025", "categoria": "Ricerca", "fascia_importo": "(50-100]", "numero_transazioni": 760}, {"anno": "2025", "categoria": "Ricerca", "fascia_importo": "(500-1000]", "numero_transazioni": 11608}, {"anno": "2025", "categoria": "Ricerca", "fascia_importo": ">1000", "numero_transazioni": 3376}, {"anno": "2025", "categoria": "Salute centrale", "fascia_importo": "(0-25]", "numero_transazioni": 3000388}, {"anno": "2025", "categoria": "Salute centrale", "fascia_importo": "(100-200]", "numero_transazioni": 801179}, {"anno": "2025", "categoria": "Salute centrale", "fascia_importo": "(200-500]", "numero_transazioni": 138927}, {"anno": "2025", "categoria": "Salute centrale", "fascia_importo": "(25-50]", "numero_transazioni": 2556464}, {"anno": "2025", "categoria": "Salute centrale", "fascia_importo": "(50-100]", "numero_transazioni": 459341}, {"anno": "2025", "categoria": "Salute centrale", "fascia_importo": "(500-1000]", "numero_transazioni": 16444}, {"anno": "2025", "categoria": "Salute centrale", "fascia_importo": ">1000", "numero_transazioni": 33183}, {"anno": "2025", "categoria": "Salute locale", "fascia_importo": "(0-25]", "numero_transazioni": 5871804}, {"anno": "2025", "categoria": "Salute locale", "fascia_importo": "(100-200]", "numero_transazioni": 1033305}, {"anno": "2025", "categoria": "Salute locale", "fascia_importo": "(200-500]", "numero_transazioni": 170147}, {"anno": "2025", "categoria": "Salute locale", "fascia_importo": "(25-50]", "numero_transazioni": 5373531}, {"anno": "2025", "categoria": "Salute locale", "fascia_importo": "(50-100]", "numero_transazioni": 1579883}, {"anno": "2025", "categoria": "Salute locale", "fascia_importo": "(500-1000]", "numero_transazioni": 28744}, {"anno": "2025", "categoria": "Salute locale", "fascia_importo": ">1000", "numero_transazioni": 40938}, {"anno": "2025", "categoria": "Salute regionale", "fascia_importo": "(0-25]", "numero_transazioni": 42477}, {"anno": "2025", "categoria": "Salute regionale", "fascia_importo": "(200-500]", "numero_transazioni": 36}, {"anno": "2025", "categoria": "Salute regionale", "fascia_importo": "(25-50]", "numero_transazioni": 1246}, {"anno": "2025", "categoria": "Salute regionale", "fascia_importo": "(50-100]", "numero_transazioni": 5}, {"anno": "2025", "categoria": "Salute regionale", "fascia_importo": "(500-1000]", "numero_transazioni": 128}, {"anno": "2025", "categoria": "Salute regionale", "fascia_importo": ">1000", "numero_transazioni": 716}, {"anno": "2025", "categoria": "Salute servizi", "fascia_importo": "(0-25]", "numero_transazioni": 100815}, {"anno": "2025", "categoria": "Salute servizi", "fascia_importo": "(100-200]", "numero_transazioni": 40334}, {"anno": "2025", "categoria": "Salute servizi", "fascia_importo": "(200-500]", "numero_transazioni": 48712}, {"anno": "2025", "categoria": "Salute servizi", "fascia_importo": "(25-50]", "numero_transazioni": 66709}, {"anno": "2025", "categoria": "Salute servizi", "fascia_importo": "(50-100]", "numero_transazioni": 45135}, {"anno": "2025", "categoria": "Salute servizi", "fascia_importo": "(500-1000]", "numero_transazioni": 21545}, {"anno": "2025", "categoria": "Salute servizi", "fascia_importo": ">1000", "numero_transazioni": 70766}, {"anno": "2025", "categoria": "Scuola", "fascia_importo": "(0-25]", "numero_transazioni": 10445532}, {"anno": "2025", "categoria": "Scuola", "fascia_importo": "(100-200]", "numero_transazioni": 1712444}, {"anno": "2025", "categoria": "Scuola", "fascia_importo": "(200-500]", "numero_transazioni": 1264326}, {"anno": "2025", "categoria": "Scuola", "fascia_importo": "(25-50]", "numero_transazioni": 3336569}, {"anno": "2025", "categoria": "Scuola", "fascia_importo": "(50-100]", "numero_transazioni": 1667078}, {"anno": "2025", "categoria": "Scuola", "fascia_importo": "(500-1000]", "numero_transazioni": 155438}, {"anno": "2025", "categoria": "Scuola", "fascia_importo": ">1000", "numero_transazioni": 27276}, {"anno": "2025", "categoria": "Tutte", "fascia_importo": "(0-25]", "numero_transazioni": 115809045}, {"anno": "2025", "categoria": "Tutte", "fascia_importo": "(100-200]", "numero_transazioni": 87121376}, {"anno": "2025", "categoria": "Tutte", "fascia_importo": "(200-500]", "numero_transazioni": 52972322}, {"anno": "2025", "categoria": "Tutte", "fascia_importo": "(25-50]", "numero_transazioni": 79001926}, {"anno": "2025", "categoria": "Tutte", "fascia_importo": "(50-100]", "numero_transazioni": 94138277}, {"anno": "2025", "categoria": "Tutte", "fascia_importo": "(500-1000]", "numero_transazioni": 11978854}, {"anno": "2025", "categoria": "Tutte", "fascia_importo": ">1000", "numero_transazioni": 7654159}, {"anno": "2025", "categoria": "Università", "fascia_importo": "(0-25]", "numero_transazioni": 1016808}, {"anno": "2025", "categoria": "Università", "fascia_importo": "(100-200]", "numero_transazioni": 1728868}, {"anno": "2025", "categoria": "Università", "fascia_importo": "(200-500]", "numero_transazioni": 1395206}, {"anno": "2025", "categoria": "Università", "fascia_importo": "(25-50]", "numero_transazioni": 820286}, {"anno": "2025", "categoria": "Università", "fascia_importo": "(50-100]", "numero_transazioni": 457527}, {"anno": "2025", "categoria": "Università", "fascia_importo": "(500-1000]", "numero_transazioni": 1065698}, {"anno": "2025", "categoria": "Università", "fascia_importo": ">1000", "numero_transazioni": 698773}, {"anno": "2025", "categoria": "Utility", "fascia_importo": "(0-25]", "numero_transazioni": 15594891}, {"anno": "2025", "categoria": "Utility", "fascia_importo": "(100-200]", "numero_transazioni": 37957498}, {"anno": "2025", "categoria": "Utility", "fascia_importo": "(200-500]", "numero_transazioni": 16395778}, {"anno": "2025", "categoria": "Utility", "fascia_importo": "(25-50]", "numero_transazioni": 29483536}, {"anno": "2025", "categoria": "Utility", "fascia_importo": "(50-100]", "numero_transazioni": 45255490}, {"anno": "2025", "categoria": "Utility", "fascia_importo": "(500-1000]", "numero_transazioni": 3571597}, {"anno": "2025", "categoria": "Utility", "fascia_importo": ">1000", "numero_transazioni": 2739424}, {"anno": "2026", "categoria": "ACI", "fascia_importo": "(0-25]", "numero_transazioni": 6266152}, {"anno": "2026", "categoria": "ACI", "fascia_importo": "(100-200]", "numero_transazioni": 6349278}, {"anno": "2026", "categoria": "ACI", "fascia_importo": "(200-500]", "numero_transazioni": 5662507}, {"anno": "2026", "categoria": "ACI", "fascia_importo": "(25-50]", "numero_transazioni": 2591833}, {"anno": "2026", "categoria": "ACI", "fascia_importo": "(50-100]", "numero_transazioni": 2139620}, {"anno": "2026", "categoria": "ACI", "fascia_importo": "(500-1000]", "numero_transazioni": 558157}, {"anno": "2026", "categoria": "ACI", "fascia_importo": ">1000", "numero_transazioni": 57909}, {"anno": "2026", "categoria": "Altri enti territoriali", "fascia_importo": "(0-25]", "numero_transazioni": 927969}, {"anno": "2026", "categoria": "Altri enti territoriali", "fascia_importo": "(100-200]", "numero_transazioni": 516054}, {"anno": "2026", "categoria": "Altri enti territoriali", "fascia_importo": "(200-500]", "numero_transazioni": 331550}, {"anno": "2026", "categoria": "Altri enti territoriali", "fascia_importo": "(25-50]", "numero_transazioni": 553797}, {"anno": "2026", "categoria": "Altri enti territoriali", "fascia_importo": "(50-100]", "numero_transazioni": 595777}, {"anno": "2026", "categoria": "Altri enti territoriali", "fascia_importo": "(500-1000]", "numero_transazioni": 64595}, {"anno": "2026", "categoria": "Altri enti territoriali", "fascia_importo": ">1000", "numero_transazioni": 71645}, {"anno": "2026", "categoria": "Comuni", "fascia_importo": "(0-25]", "numero_transazioni": 4251629}, {"anno": "2026", "categoria": "Comuni", "fascia_importo": "(100-200]", "numero_transazioni": 4761749}, {"anno": "2026", "categoria": "Comuni", "fascia_importo": "(200-500]", "numero_transazioni": 2410034}, {"anno": "2026", "categoria": "Comuni", "fascia_importo": "(25-50]", "numero_transazioni": 5947260}, {"anno": "2026", "categoria": "Comuni", "fascia_importo": "(50-100]", "numero_transazioni": 6694586}, {"anno": "2026", "categoria": "Comuni", "fascia_importo": "(500-1000]", "numero_transazioni": 606041}, {"anno": "2026", "categoria": "Comuni", "fascia_importo": ">1000", "numero_transazioni": 398519}, {"anno": "2026", "categoria": "Consorzi universitari", "fascia_importo": "(0-25]", "numero_transazioni": 27972}, {"anno": "2026", "categoria": "Consorzi universitari", "fascia_importo": "(100-200]", "numero_transazioni": 85908}, {"anno": "2026", "categoria": "Consorzi universitari", "fascia_importo": "(200-500]", "numero_transazioni": 16023}, {"anno": "2026", "categoria": "Consorzi universitari", "fascia_importo": "(25-50]", "numero_transazioni": 9785}, {"anno": "2026", "categoria": "Consorzi universitari", "fascia_importo": "(50-100]", "numero_transazioni": 7711}, {"anno": "2026", "categoria": "Consorzi universitari", "fascia_importo": "(500-1000]", "numero_transazioni": 1530}, {"anno": "2026", "categoria": "Consorzi universitari", "fascia_importo": ">1000", "numero_transazioni": 2208}, {"anno": "2026", "categoria": "Enti comunali", "fascia_importo": "(0-25]", "numero_transazioni": 2538}, {"anno": "2026", "categoria": "Enti comunali", "fascia_importo": "(100-200]", "numero_transazioni": 11272}, {"anno": "2026", "categoria": "Enti comunali", "fascia_importo": "(200-500]", "numero_transazioni": 6728}, {"anno": "2026", "categoria": "Enti comunali", "fascia_importo": "(25-50]", "numero_transazioni": 10179}, {"anno": "2026", "categoria": "Enti comunali", "fascia_importo": "(50-100]", "numero_transazioni": 12347}, {"anno": "2026", "categoria": "Enti comunali", "fascia_importo": "(500-1000]", "numero_transazioni": 846}, {"anno": "2026", "categoria": "Enti comunali", "fascia_importo": ">1000", "numero_transazioni": 806}, {"anno": "2026", "categoria": "Enti provinciali", "fascia_importo": "(0-25]", "numero_transazioni": 335}, {"anno": "2026", "categoria": "Enti provinciali", "fascia_importo": "(100-200]", "numero_transazioni": 334}, {"anno": "2026", "categoria": "Enti provinciali", "fascia_importo": "(200-500]", "numero_transazioni": 23}, {"anno": "2026", "categoria": "Enti provinciali", "fascia_importo": "(25-50]", "numero_transazioni": 7}, {"anno": "2026", "categoria": "Enti provinciali", "fascia_importo": "(50-100]", "numero_transazioni": 103}, {"anno": "2026", "categoria": "Enti provinciali", "fascia_importo": "(500-1000]", "numero_transazioni": 275}, {"anno": "2026", "categoria": "Enti provinciali", "fascia_importo": ">1000", "numero_transazioni": 160}, {"anno": "2026", "categoria": "Enti regionali", "fascia_importo": "(0-25]", "numero_transazioni": 820}, {"anno": "2026", "categoria": "Enti regionali", "fascia_importo": "(100-200]", "numero_transazioni": 34}, {"anno": "2026", "categoria": "Enti regionali", "fascia_importo": "(200-500]", "numero_transazioni": 34}, {"anno": "2026", "categoria": "Enti regionali", "fascia_importo": "(25-50]", "numero_transazioni": 7}, {"anno": "2026", "categoria": "Enti regionali", "fascia_importo": "(50-100]", "numero_transazioni": 22}, {"anno": "2026", "categoria": "Enti regionali", "fascia_importo": "(500-1000]", "numero_transazioni": 10}, {"anno": "2026", "categoria": "Enti regionali", "fascia_importo": ">1000", "numero_transazioni": 67}, {"anno": "2026", "categoria": "Ordini, collegi e consigli professionali", "fascia_importo": "(0-25]", "numero_transazioni": 247905}, {"anno": "2026", "categoria": "Ordini, collegi e consigli professionali", "fascia_importo": "(100-200]", "numero_transazioni": 985337}, {"anno": "2026", "categoria": "Ordini, collegi e consigli professionali", "fascia_importo": "(200-500]", "numero_transazioni": 383693}, {"anno": "2026", "categoria": "Ordini, collegi e consigli professionali", "fascia_importo": "(25-50]", "numero_transazioni": 204724}, {"anno": "2026", "categoria": "Ordini, collegi e consigli professionali", "fascia_importo": "(50-100]", "numero_transazioni": 543139}, {"anno": "2026", "categoria": "Ordini, collegi e consigli professionali", "fascia_importo": "(500-1000]", "numero_transazioni": 10223}, {"anno": "2026", "categoria": "Ordini, collegi e consigli professionali", "fascia_importo": ">1000", "numero_transazioni": 9806}, {"anno": "2026", "categoria": "Province", "fascia_importo": "(0-25]", "numero_transazioni": 66747}, {"anno": "2026", "categoria": "Province", "fascia_importo": "(100-200]", "numero_transazioni": 169628}, {"anno": "2026", "categoria": "Province", "fascia_importo": "(200-500]", "numero_transazioni": 85997}, {"anno": "2026", "categoria": "Province", "fascia_importo": "(25-50]", "numero_transazioni": 282141}, {"anno": "2026", "categoria": "Province", "fascia_importo": "(50-100]", "numero_transazioni": 198983}, {"anno": "2026", "categoria": "Province", "fascia_importo": "(500-1000]", "numero_transazioni": 18256}, {"anno": "2026", "categoria": "Province", "fascia_importo": ">1000", "numero_transazioni": 13307}, {"anno": "2026", "categoria": "Pubbliche amministrazioni centrali", "fascia_importo": "(0-25]", "numero_transazioni": 22449574}, {"anno": "2026", "categoria": "Pubbliche amministrazioni centrali", "fascia_importo": "(100-200]", "numero_transazioni": 4597975}, {"anno": "2026", "categoria": "Pubbliche amministrazioni centrali", "fascia_importo": "(200-500]", "numero_transazioni": 4093888}, {"anno": "2026", "categoria": "Pubbliche amministrazioni centrali", "fascia_importo": "(25-50]", "numero_transazioni": 7233393}, {"anno": "2026", "categoria": "Pubbliche amministrazioni centrali", "fascia_importo": "(50-100]", "numero_transazioni": 8143681}, {"anno": "2026", "categoria": "Pubbliche amministrazioni centrali", "fascia_importo": "(500-1000]", "numero_transazioni": 1576044}, {"anno": "2026", "categoria": "Pubbliche amministrazioni centrali", "fascia_importo": ">1000", "numero_transazioni": 945269}, {"anno": "2026", "categoria": "Regioni", "fascia_importo": "(0-25]", "numero_transazioni": 734308}, {"anno": "2026", "categoria": "Regioni", "fascia_importo": "(100-200]", "numero_transazioni": 1432300}, {"anno": "2026", "categoria": "Regioni", "fascia_importo": "(200-500]", "numero_transazioni": 1282284}, {"anno": "2026", "categoria": "Regioni", "fascia_importo": "(25-50]", "numero_transazioni": 591703}, {"anno": "2026", "categoria": "Regioni", "fascia_importo": "(50-100]", "numero_transazioni": 555531}, {"anno": "2026", "categoria": "Regioni", "fascia_importo": "(500-1000]", "numero_transazioni": 96510}, {"anno": "2026", "categoria": "Regioni", "fascia_importo": ">1000", "numero_transazioni": 46677}, {"anno": "2026", "categoria": "Ricerca", "fascia_importo": "(0-25]", "numero_transazioni": 6494}, {"anno": "2026", "categoria": "Ricerca", "fascia_importo": "(100-200]", "numero_transazioni": 7422}, {"anno": "2026", "categoria": "Ricerca", "fascia_importo": "(200-500]", "numero_transazioni": 3129}, {"anno": "2026", "categoria": "Ricerca", "fascia_importo": "(25-50]", "numero_transazioni": 7372}, {"anno": "2026", "categoria": "Ricerca", "fascia_importo": "(50-100]", "numero_transazioni": 217}, {"anno": "2026", "categoria": "Ricerca", "fascia_importo": "(500-1000]", "numero_transazioni": 7267}, {"anno": "2026", "categoria": "Ricerca", "fascia_importo": ">1000", "numero_transazioni": 1703}, {"anno": "2026", "categoria": "Salute centrale", "fascia_importo": "(0-25]", "numero_transazioni": 1150434}, {"anno": "2026", "categoria": "Salute centrale", "fascia_importo": "(100-200]", "numero_transazioni": 308913}, {"anno": "2026", "categoria": "Salute centrale", "fascia_importo": "(200-500]", "numero_transazioni": 55377}, {"anno": "2026", "categoria": "Salute centrale", "fascia_importo": "(25-50]", "numero_transazioni": 1009949}, {"anno": "2026", "categoria": "Salute centrale", "fascia_importo": "(50-100]", "numero_transazioni": 163196}, {"anno": "2026", "categoria": "Salute centrale", "fascia_importo": "(500-1000]", "numero_transazioni": 6579}, {"anno": "2026", "categoria": "Salute centrale", "fascia_importo": ">1000", "numero_transazioni": 14475}, {"anno": "2026", "categoria": "Salute locale", "fascia_importo": "(0-25]", "numero_transazioni": 2487041}, {"anno": "2026", "categoria": "Salute locale", "fascia_importo": "(100-200]", "numero_transazioni": 405935}, {"anno": "2026", "categoria": "Salute locale", "fascia_importo": "(200-500]", "numero_transazioni": 80665}, {"anno": "2026", "categoria": "Salute locale", "fascia_importo": "(25-50]", "numero_transazioni": 2404773}, {"anno": "2026", "categoria": "Salute locale", "fascia_importo": "(50-100]", "numero_transazioni": 656248}, {"anno": "2026", "categoria": "Salute locale", "fascia_importo": "(500-1000]", "numero_transazioni": 12253}, {"anno": "2026", "categoria": "Salute locale", "fascia_importo": ">1000", "numero_transazioni": 18537}, {"anno": "2026", "categoria": "Salute regionale", "fascia_importo": "(0-25]", "numero_transazioni": 14644}, {"anno": "2026", "categoria": "Salute regionale", "fascia_importo": "(100-200]", "numero_transazioni": 9}, {"anno": "2026", "categoria": "Salute regionale", "fascia_importo": "(200-500]", "numero_transazioni": 10}, {"anno": "2026", "categoria": "Salute regionale", "fascia_importo": "(25-50]", "numero_transazioni": 11}, {"anno": "2026", "categoria": "Salute regionale", "fascia_importo": "(50-100]", "numero_transazioni": 8}, {"anno": "2026", "categoria": "Salute regionale", "fascia_importo": "(500-1000]", "numero_transazioni": 31}, {"anno": "2026", "categoria": "Salute regionale", "fascia_importo": ">1000", "numero_transazioni": 252}, {"anno": "2026", "categoria": "Salute servizi", "fascia_importo": "(0-25]", "numero_transazioni": 46530}, {"anno": "2026", "categoria": "Salute servizi", "fascia_importo": "(100-200]", "numero_transazioni": 18909}, {"anno": "2026", "categoria": "Salute servizi", "fascia_importo": "(200-500]", "numero_transazioni": 22526}, {"anno": "2026", "categoria": "Salute servizi", "fascia_importo": "(25-50]", "numero_transazioni": 32971}, {"anno": "2026", "categoria": "Salute servizi", "fascia_importo": "(50-100]", "numero_transazioni": 20951}, {"anno": "2026", "categoria": "Salute servizi", "fascia_importo": "(500-1000]", "numero_transazioni": 9627}, {"anno": "2026", "categoria": "Salute servizi", "fascia_importo": ">1000", "numero_transazioni": 29321}, {"anno": "2026", "categoria": "Scuola", "fascia_importo": "(0-25]", "numero_transazioni": 4771009}, {"anno": "2026", "categoria": "Scuola", "fascia_importo": "(100-200]", "numero_transazioni": 1138631}, {"anno": "2026", "categoria": "Scuola", "fascia_importo": "(200-500]", "numero_transazioni": 882182}, {"anno": "2026", "categoria": "Scuola", "fascia_importo": "(25-50]", "numero_transazioni": 2350388}, {"anno": "2026", "categoria": "Scuola", "fascia_importo": "(50-100]", "numero_transazioni": 1095490}, {"anno": "2026", "categoria": "Scuola", "fascia_importo": "(500-1000]", "numero_transazioni": 87228}, {"anno": "2026", "categoria": "Scuola", "fascia_importo": ">1000", "numero_transazioni": 11627}, {"anno": "2026", "categoria": "Tutte", "fascia_importo": "(0-25]", "numero_transazioni": 49997170}, {"anno": "2026", "categoria": "Tutte", "fascia_importo": "(100-200]", "numero_transazioni": 38440665}, {"anno": "2026", "categoria": "Tutte", "fascia_importo": "(200-500]", "numero_transazioni": 24926564}, {"anno": "2026", "categoria": "Tutte", "fascia_importo": "(25-50]", "numero_transazioni": 35104832}, {"anno": "2026", "categoria": "Tutte", "fascia_importo": "(50-100]", "numero_transazioni": 40077787}, {"anno": "2026", "categoria": "Tutte", "fascia_importo": "(500-1000]", "numero_transazioni": 5442690}, {"anno": "2026", "categoria": "Tutte", "fascia_importo": ">1000", "numero_transazioni": 3186459}, {"anno": "2026", "categoria": "Università", "fascia_importo": "(0-25]", "numero_transazioni": 354506}, {"anno": "2026", "categoria": "Università", "fascia_importo": "(100-200]", "numero_transazioni": 399072}, {"anno": "2026", "categoria": "Università", "fascia_importo": "(200-500]", "numero_transazioni": 619575}, {"anno": "2026", "categoria": "Università", "fascia_importo": "(25-50]", "numero_transazioni": 355932}, {"anno": "2026", "categoria": "Università", "fascia_importo": "(50-100]", "numero_transazioni": 209613}, {"anno": "2026", "categoria": "Università", "fascia_importo": "(500-1000]", "numero_transazioni": 515785}, {"anno": "2026", "categoria": "Università", "fascia_importo": ">1000", "numero_transazioni": 399344}, {"anno": "2026", "categoria": "Utility", "fascia_importo": "(0-25]", "numero_transazioni": 6189674}, {"anno": "2026", "categoria": "Utility", "fascia_importo": "(100-200]", "numero_transazioni": 17249221}, {"anno": "2026", "categoria": "Utility", "fascia_importo": "(200-500]", "numero_transazioni": 8988367}, {"anno": "2026", "categoria": "Utility", "fascia_importo": "(25-50]", "numero_transazioni": 11516757}, {"anno": "2026", "categoria": "Utility", "fascia_importo": "(50-100]", "numero_transazioni": 19038678}, {"anno": "2026", "categoria": "Utility", "fascia_importo": "(500-1000]", "numero_transazioni": 1870953}, {"anno": "2026", "categoria": "Utility", "fascia_importo": ">1000", "numero_transazioni": 1164536}, {"anno": "Complessivo", "categoria": "ACI", "fascia_importo": "(0-25]", "numero_transazioni": 77791928}, {"anno": "Complessivo", "categoria": "ACI", "fascia_importo": "(100-200]", "numero_transazioni": 86658298}, {"anno": "Complessivo", "categoria": "ACI", "fascia_importo": "(200-500]", "numero_transazioni": 76449553}, {"anno": "Complessivo", "categoria": "ACI", "fascia_importo": "(25-50]", "numero_transazioni": 31557272}, {"anno": "Complessivo", "categoria": "ACI", "fascia_importo": "(50-100]", "numero_transazioni": 24430103}, {"anno": "Complessivo", "categoria": "ACI", "fascia_importo": "(500-1000]", "numero_transazioni": 7439534}, {"anno": "Complessivo", "categoria": "ACI", "fascia_importo": ">1000", "numero_transazioni": 615611}, {"anno": "Complessivo", "categoria": "Altri enti territoriali", "fascia_importo": "(0-25]", "numero_transazioni": 6040222}, {"anno": "Complessivo", "categoria": "Altri enti territoriali", "fascia_importo": "(100-200]", "numero_transazioni": 5182925}, {"anno": "Complessivo", "categoria": "Altri enti territoriali", "fascia_importo": "(200-500]", "numero_transazioni": 3151569}, {"anno": "Complessivo", "categoria": "Altri enti territoriali", "fascia_importo": "(25-50]", "numero_transazioni": 6407151}, {"anno": "Complessivo", "categoria": "Altri enti territoriali", "fascia_importo": "(50-100]", "numero_transazioni": 6202909}, {"anno": "Complessivo", "categoria": "Altri enti territoriali", "fascia_importo": "(500-1000]", "numero_transazioni": 513393}, {"anno": "Complessivo", "categoria": "Altri enti territoriali", "fascia_importo": ">1000", "numero_transazioni": 569874}, {"anno": "Complessivo", "categoria": "Comuni", "fascia_importo": "(0-25]", "numero_transazioni": 38842814}, {"anno": "Complessivo", "categoria": "Comuni", "fascia_importo": "(100-200]", "numero_transazioni": 53627320}, {"anno": "Complessivo", "categoria": "Comuni", "fascia_importo": "(200-500]", "numero_transazioni": 27793464}, {"anno": "Complessivo", "categoria": "Comuni", "fascia_importo": "(25-50]", "numero_transazioni": 61988985}, {"anno": "Complessivo", "categoria": "Comuni", "fascia_importo": "(50-100]", "numero_transazioni": 76312769}, {"anno": "Complessivo", "categoria": "Comuni", "fascia_importo": "(500-1000]", "numero_transazioni": 5703961}, {"anno": "Complessivo", "categoria": "Comuni", "fascia_importo": ">1000", "numero_transazioni": 3698481}, {"anno": "Complessivo", "categoria": "Consorzi universitari", "fascia_importo": "(0-25]", "numero_transazioni": 260698}, {"anno": "Complessivo", "categoria": "Consorzi universitari", "fascia_importo": "(100-200]", "numero_transazioni": 927235}, {"anno": "Complessivo", "categoria": "Consorzi universitari", "fascia_importo": "(200-500]", "numero_transazioni": 146801}, {"anno": "Complessivo", "categoria": "Consorzi universitari", "fascia_importo": "(25-50]", "numero_transazioni": 82886}, {"anno": "Complessivo", "categoria": "Consorzi universitari", "fascia_importo": "(50-100]", "numero_transazioni": 67946}, {"anno": "Complessivo", "categoria": "Consorzi universitari", "fascia_importo": "(500-1000]", "numero_transazioni": 22328}, {"anno": "Complessivo", "categoria": "Consorzi universitari", "fascia_importo": ">1000", "numero_transazioni": 17803}, {"anno": "Complessivo", "categoria": "Enti comunali", "fascia_importo": "(0-25]", "numero_transazioni": 164577}, {"anno": "Complessivo", "categoria": "Enti comunali", "fascia_importo": "(100-200]", "numero_transazioni": 206662}, {"anno": "Complessivo", "categoria": "Enti comunali", "fascia_importo": "(200-500]", "numero_transazioni": 87618}, {"anno": "Complessivo", "categoria": "Enti comunali", "fascia_importo": "(25-50]", "numero_transazioni": 224328}, {"anno": "Complessivo", "categoria": "Enti comunali", "fascia_importo": "(50-100]", "numero_transazioni": 270175}, {"anno": "Complessivo", "categoria": "Enti comunali", "fascia_importo": "(500-1000]", "numero_transazioni": 12467}, {"anno": "Complessivo", "categoria": "Enti comunali", "fascia_importo": ">1000", "numero_transazioni": 10831}, {"anno": "Complessivo", "categoria": "Enti donazioni", "fascia_importo": "(0-25]", "numero_transazioni": 13707}, {"anno": "Complessivo", "categoria": "Enti donazioni", "fascia_importo": "(100-200]", "numero_transazioni": 189}, {"anno": "Complessivo", "categoria": "Enti donazioni", "fascia_importo": "(25-50]", "numero_transazioni": 2400}, {"anno": "Complessivo", "categoria": "Enti donazioni", "fascia_importo": "(50-100]", "numero_transazioni": 857}, {"anno": "Complessivo", "categoria": "Enti provinciali", "fascia_importo": "(0-25]", "numero_transazioni": 9411}, {"anno": "Complessivo", "categoria": "Enti provinciali", "fascia_importo": "(100-200]", "numero_transazioni": 3283}, {"anno": "Complessivo", "categoria": "Enti provinciali", "fascia_importo": "(200-500]", "numero_transazioni": 2526}, {"anno": "Complessivo", "categoria": "Enti provinciali", "fascia_importo": "(25-50]", "numero_transazioni": 14153}, {"anno": "Complessivo", "categoria": "Enti provinciali", "fascia_importo": "(50-100]", "numero_transazioni": 11705}, {"anno": "Complessivo", "categoria": "Enti provinciali", "fascia_importo": "(500-1000]", "numero_transazioni": 1680}, {"anno": "Complessivo", "categoria": "Enti provinciali", "fascia_importo": ">1000", "numero_transazioni": 1420}, {"anno": "Complessivo", "categoria": "Enti regionali", "fascia_importo": "(0-25]", "numero_transazioni": 20990}, {"anno": "Complessivo", "categoria": "Enti regionali", "fascia_importo": "(100-200]", "numero_transazioni": 256}, {"anno": "Complessivo", "categoria": "Enti regionali", "fascia_importo": "(200-500]", "numero_transazioni": 302}, {"anno": "Complessivo", "categoria": "Enti regionali", "fascia_importo": "(25-50]", "numero_transazioni": 110}, {"anno": "Complessivo", "categoria": "Enti regionali", "fascia_importo": "(50-100]", "numero_transazioni": 218}, {"anno": "Complessivo", "categoria": "Enti regionali", "fascia_importo": "(500-1000]", "numero_transazioni": 138}, {"anno": "Complessivo", "categoria": "Enti regionali", "fascia_importo": ">1000", "numero_transazioni": 705}, {"anno": "Complessivo", "categoria": "Ordini, collegi e consigli professionali", "fascia_importo": "(0-25]", "numero_transazioni": 2683553}, {"anno": "Complessivo", "categoria": "Ordini, collegi e consigli professionali", "fascia_importo": "(100-200]", "numero_transazioni": 6932862}, {"anno": "Complessivo", "categoria": "Ordini, collegi e consigli professionali", "fascia_importo": "(200-500]", "numero_transazioni": 2555521}, {"anno": "Complessivo", "categoria": "Ordini, collegi e consigli professionali", "fascia_importo": "(25-50]", "numero_transazioni": 1631992}, {"anno": "Complessivo", "categoria": "Ordini, collegi e consigli professionali", "fascia_importo": "(50-100]", "numero_transazioni": 5042156}, {"anno": "Complessivo", "categoria": "Ordini, collegi e consigli professionali", "fascia_importo": "(500-1000]", "numero_transazioni": 67383}, {"anno": "Complessivo", "categoria": "Ordini, collegi e consigli professionali", "fascia_importo": ">1000", "numero_transazioni": 63943}, {"anno": "Complessivo", "categoria": "Province", "fascia_importo": "(0-25]", "numero_transazioni": 916531}, {"anno": "Complessivo", "categoria": "Province", "fascia_importo": "(100-200]", "numero_transazioni": 1983331}, {"anno": "Complessivo", "categoria": "Province", "fascia_importo": "(200-500]", "numero_transazioni": 888570}, {"anno": "Complessivo", "categoria": "Province", "fascia_importo": "(25-50]", "numero_transazioni": 3450374}, {"anno": "Complessivo", "categoria": "Province", "fascia_importo": "(50-100]", "numero_transazioni": 2229487}, {"anno": "Complessivo", "categoria": "Province", "fascia_importo": "(500-1000]", "numero_transazioni": 171443}, {"anno": "Complessivo", "categoria": "Province", "fascia_importo": ">1000", "numero_transazioni": 123818}, {"anno": "Complessivo", "categoria": "Pubbliche amministrazioni centrali", "fascia_importo": "(0-25]", "numero_transazioni": 220237029}, {"anno": "Complessivo", "categoria": "Pubbliche amministrazioni centrali", "fascia_importo": "(100-200]", "numero_transazioni": 49203353}, {"anno": "Complessivo", "categoria": "Pubbliche amministrazioni centrali", "fascia_importo": "(200-500]", "numero_transazioni": 45225487}, {"anno": "Complessivo", "categoria": "Pubbliche amministrazioni centrali", "fascia_importo": "(25-50]", "numero_transazioni": 64023187}, {"anno": "Complessivo", "categoria": "Pubbliche amministrazioni centrali", "fascia_importo": "(50-100]", "numero_transazioni": 79518415}, {"anno": "Complessivo", "categoria": "Pubbliche amministrazioni centrali", "fascia_importo": "(500-1000]", "numero_transazioni": 16916911}, {"anno": "Complessivo", "categoria": "Pubbliche amministrazioni centrali", "fascia_importo": ">1000", "numero_transazioni": 10804082}, {"anno": "Complessivo", "categoria": "Regioni", "fascia_importo": "(0-25]", "numero_transazioni": 7080074}, {"anno": "Complessivo", "categoria": "Regioni", "fascia_importo": "(100-200]", "numero_transazioni": 16533094}, {"anno": "Complessivo", "categoria": "Regioni", "fascia_importo": "(200-500]", "numero_transazioni": 14233335}, {"anno": "Complessivo", "categoria": "Regioni", "fascia_importo": "(25-50]", "numero_transazioni": 5869742}, {"anno": "Complessivo", "categoria": "Regioni", "fascia_importo": "(50-100]", "numero_transazioni": 6151403}, {"anno": "Complessivo", "categoria": "Regioni", "fascia_importo": "(500-1000]", "numero_transazioni": 1071515}, {"anno": "Complessivo", "categoria": "Regioni", "fascia_importo": ">1000", "numero_transazioni": 446991}, {"anno": "Complessivo", "categoria": "Ricerca", "fascia_importo": "(0-25]", "numero_transazioni": 52136}, {"anno": "Complessivo", "categoria": "Ricerca", "fascia_importo": "(100-200]", "numero_transazioni": 21660}, {"anno": "Complessivo", "categoria": "Ricerca", "fascia_importo": "(200-500]", "numero_transazioni": 15052}, {"anno": "Complessivo", "categoria": "Ricerca", "fascia_importo": "(25-50]", "numero_transazioni": 9022}, {"anno": "Complessivo", "categoria": "Ricerca", "fascia_importo": "(50-100]", "numero_transazioni": 2457}, {"anno": "Complessivo", "categoria": "Ricerca", "fascia_importo": "(500-1000]", "numero_transazioni": 21143}, {"anno": "Complessivo", "categoria": "Ricerca", "fascia_importo": ">1000", "numero_transazioni": 9186}, {"anno": "Complessivo", "categoria": "Salute centrale", "fascia_importo": "(0-25]", "numero_transazioni": 10236235}, {"anno": "Complessivo", "categoria": "Salute centrale", "fascia_importo": "(100-200]", "numero_transazioni": 2745282}, {"anno": "Complessivo", "categoria": "Salute centrale", "fascia_importo": "(200-500]", "numero_transazioni": 481697}, {"anno": "Complessivo", "categoria": "Salute centrale", "fascia_importo": "(25-50]", "numero_transazioni": 7676067}, {"anno": "Complessivo", "categoria": "Salute centrale", "fascia_importo": "(50-100]", "numero_transazioni": 1574829}, {"anno": "Complessivo", "categoria": "Salute centrale", "fascia_importo": "(500-1000]", "numero_transazioni": 58842}, {"anno": "Complessivo", "categoria": "Salute centrale", "fascia_importo": ">1000", "numero_transazioni": 129862}, {"anno": "Complessivo", "categoria": "Salute locale", "fascia_importo": "(0-25]", "numero_transazioni": 22467273}, {"anno": "Complessivo", "categoria": "Salute locale", "fascia_importo": "(100-200]", "numero_transazioni": 3786786}, {"anno": "Complessivo", "categoria": "Salute locale", "fascia_importo": "(200-500]", "numero_transazioni": 630604}, {"anno": "Complessivo", "categoria": "Salute locale", "fascia_importo": "(25-50]", "numero_transazioni": 18605912}, {"anno": "Complessivo", "categoria": "Salute locale", "fascia_importo": "(50-100]", "numero_transazioni": 5966162}, {"anno": "Complessivo", "categoria": "Salute locale", "fascia_importo": "(500-1000]", "numero_transazioni": 118853}, {"anno": "Complessivo", "categoria": "Salute locale", "fascia_importo": ">1000", "numero_transazioni": 163740}, {"anno": "Complessivo", "categoria": "Salute regionale", "fascia_importo": "(0-25]", "numero_transazioni": 155753}, {"anno": "Complessivo", "categoria": "Salute regionale", "fascia_importo": "(100-200]", "numero_transazioni": 1151}, {"anno": "Complessivo", "categoria": "Salute regionale", "fascia_importo": "(200-500]", "numero_transazioni": 698}, {"anno": "Complessivo", "categoria": "Salute regionale", "fascia_importo": "(25-50]", "numero_transazioni": 1304}, {"anno": "Complessivo", "categoria": "Salute regionale", "fascia_importo": "(50-100]", "numero_transazioni": 86}, {"anno": "Complessivo", "categoria": "Salute regionale", "fascia_importo": "(500-1000]", "numero_transazioni": 605}, {"anno": "Complessivo", "categoria": "Salute regionale", "fascia_importo": ">1000", "numero_transazioni": 2480}, {"anno": "Complessivo", "categoria": "Salute servizi", "fascia_importo": "(0-25]", "numero_transazioni": 499301}, {"anno": "Complessivo", "categoria": "Salute servizi", "fascia_importo": "(100-200]", "numero_transazioni": 189712}, {"anno": "Complessivo", "categoria": "Salute servizi", "fascia_importo": "(200-500]", "numero_transazioni": 214228}, {"anno": "Complessivo", "categoria": "Salute servizi", "fascia_importo": "(25-50]", "numero_transazioni": 326360}, {"anno": "Complessivo", "categoria": "Salute servizi", "fascia_importo": "(50-100]", "numero_transazioni": 224883}, {"anno": "Complessivo", "categoria": "Salute servizi", "fascia_importo": "(500-1000]", "numero_transazioni": 94292}, {"anno": "Complessivo", "categoria": "Salute servizi", "fascia_importo": ">1000", "numero_transazioni": 335614}, {"anno": "Complessivo", "categoria": "Scuola", "fascia_importo": "(0-25]", "numero_transazioni": 43361538}, {"anno": "Complessivo", "categoria": "Scuola", "fascia_importo": "(100-200]", "numero_transazioni": 7575031}, {"anno": "Complessivo", "categoria": "Scuola", "fascia_importo": "(200-500]", "numero_transazioni": 5014239}, {"anno": "Complessivo", "categoria": "Scuola", "fascia_importo": "(25-50]", "numero_transazioni": 13776700}, {"anno": "Complessivo", "categoria": "Scuola", "fascia_importo": "(50-100]", "numero_transazioni": 7504903}, {"anno": "Complessivo", "categoria": "Scuola", "fascia_importo": "(500-1000]", "numero_transazioni": 648451}, {"anno": "Complessivo", "categoria": "Scuola", "fascia_importo": ">1000", "numero_transazioni": 115836}, {"anno": "Complessivo", "categoria": "Tutte", "fascia_importo": "(0-25]", "numero_transazioni": 508738482}, {"anno": "Complessivo", "categoria": "Tutte", "fascia_importo": "(100-200]", "numero_transazioni": 411056688}, {"anno": "Complessivo", "categoria": "Tutte", "fascia_importo": "(200-500]", "numero_transazioni": 260478146}, {"anno": "Complessivo", "categoria": "Tutte", "fascia_importo": "(25-50]", "numero_transazioni": 361843996}, {"anno": "Complessivo", "categoria": "Tutte", "fascia_importo": "(50-100]", "numero_transazioni": 412827330}, {"anno": "Complessivo", "categoria": "Tutte", "fascia_importo": "(500-1000]", "numero_transazioni": 53969656}, {"anno": "Complessivo", "categoria": "Tutte", "fascia_importo": ">1000", "numero_transazioni": 31969999}, {"anno": "Complessivo", "categoria": "Università", "fascia_importo": "(0-25]", "numero_transazioni": 5536103}, {"anno": "Complessivo", "categoria": "Università", "fascia_importo": "(100-200]", "numero_transazioni": 9038875}, {"anno": "Complessivo", "categoria": "Università", "fascia_importo": "(200-500]", "numero_transazioni": 7300854}, {"anno": "Complessivo", "categoria": "Università", "fascia_importo": "(25-50]", "numero_transazioni": 4503559}, {"anno": "Complessivo", "categoria": "Università", "fascia_importo": "(50-100]", "numero_transazioni": 2920027}, {"anno": "Complessivo", "categoria": "Università", "fascia_importo": "(500-1000]", "numero_transazioni": 6207837}, {"anno": "Complessivo", "categoria": "Università", "fascia_importo": ">1000", "numero_transazioni": 3626328}, {"anno": "Complessivo", "categoria": "Utility", "fascia_importo": "(0-25]", "numero_transazioni": 72367434}, {"anno": "Complessivo", "categoria": "Utility", "fascia_importo": "(100-200]", "numero_transazioni": 166435758}, {"anno": "Complessivo", "categoria": "Utility", "fascia_importo": "(200-500]", "numero_transazioni": 76283741}, {"anno": "Complessivo", "categoria": "Utility", "fascia_importo": "(25-50]", "numero_transazioni": 141690369}, {"anno": "Complessivo", "categoria": "Utility", "fascia_importo": "(50-100]", "numero_transazioni": 194393349}, {"anno": "Complessivo", "categoria": "Utility", "fascia_importo": "(500-1000]", "numero_transazioni": 14898174}, {"anno": "Complessivo", "categoria": "Utility", "fascia_importo": ">1000", "numero_transazioni": 11232829}]